EBDM/__init__.py
EBDM/categories.py
EBDM/distance.py
EBDM/feature_functions.py
EBDM/features.py
EBDM/nominal_data.py
EBDM/ordinal_data.py
EBDM-1.0.0.dist-info/DESCRIPTION.rst
EBDM-1.0.0.dist-info/METADATA
EBDM-1.0.0.dist-info/RECORD
EBDM-1.0.0.dist-info/WHEEL
EBDM-1.0.0.dist-info/metadata.json
EBDM-1.0.0.dist-info/top_level.txt
