Metadata-Version: 2.0
Name: EBDM
Version: 1.0.0
Summary: Entropy Based Distance Metric
Home-page: https://github.com/Rohit2706/EBDM
Author: Rohit Jain
Author-email: rohitjain2706@gmail.com
License: UNKNOWN
Keywords: entropy questionnnaire distance
Platform: UNKNOWN
Classifier: Programming Language :: Python :: 3
Classifier: License :: OSI Approved :: MIT License
Classifier: Operating System :: OS Independent
